[
      {
            "No": "1.",
            "Gambar": "PhotoTop100Film/1.png",
            "Judul": " The Shawshank Redemption ",
            "Tahun": "1994",
            "Rating": "9,2  "
      },
      {
            "No": "2.",
            "Gambar": "PhotoTop100Film/2.png",
            "Judul": " The Godfather ",
            "Tahun": "1972",
            "Rating": "9,2  "
      },
      {
            "No": "3.",
            "Gambar": "PhotoTop100Film/3.png",
            "Judul": " The Dark Knight ",
            "Tahun": "2008",
            "Rating": "9,0  "
      },
      {
            "No": "4.",
            "Gambar": "PhotoTop100Film/4.png",
            "Judul": " The Godfather Part II ",
            "Tahun": "1974",
            "Rating": "9,0  "
      },
      {
            "No": "5.",
            "Gambar": "PhotoTop100Film/5.png",
            "Judul": " 12 Angry Men ",
            "Tahun": "1957",
            "Rating": "9,0  "
      },
      {
            "No": "6.",
            "Gambar": "PhotoTop100Film/6.png",
            "Judul": " Schindler's List ",
            "Tahun": "1993",
            "Rating": "8,9  "
      },
      {
            "No": "7.",
            "Gambar": "PhotoTop100Film/7.png",
            "Judul": " The Lord of the Rings: The Return of the King ",
            "Tahun": "2003",
            "Rating": "8,9  "
      },
      {
            "No": "8.",
            "Gambar": "PhotoTop100Film/8.png",
            "Judul": " Pulp Fiction ",
            "Tahun": "1994",
            "Rating": "8,8  "
      },
      {
            "No": "9.",
            "Gambar": "PhotoTop100Film/9.png",
            "Judul": " The Lord of the Rings: The Fellowship of the Ring ",
            "Tahun": "2001",
            "Rating": "8,8  "
      },
      {
            "No": "10.",
            "Gambar": "PhotoTop100Film/10.png",
            "Judul": " The Good, the Bad and the Ugly ",
            "Tahun": "1966",
            "Rating": "8,8  "
      },
      {
            "No": "11.",
            "Gambar": "PhotoTop100Film/11.png",
            "Judul": " Forrest Gump ",
            "Tahun": "1994",
            "Rating": "8,8  "
      },
      {
            "No": "12.",
            "Gambar": "PhotoTop100Film/12.png",
            "Judul": " Fight Club ",
            "Tahun": "1999",
            "Rating": "8,7  "
      },
      {
            "No": "13.",
            "Gambar": "PhotoTop100Film/13.png",
            "Judul": " The Lord of the Rings: The Two Towers ",
            "Tahun": "2002",
            "Rating": "8,7  "
      },
      {
            "No": "14.",
            "Gambar": "PhotoTop100Film/14.png",
            "Judul": " Inception ",
            "Tahun": "2010",
            "Rating": "8,7  "
      },
      {
            "No": "15.",
            "Gambar": "PhotoTop100Film/15.png",
            "Judul": " Star Wars: Episode V - The Empire Strikes Back ",
            "Tahun": "1980",
            "Rating": "8,7  "
      },
      {
            "No": "16.",
            "Gambar": "PhotoTop100Film/16.png",
            "Judul": " The Matrix ",
            "Tahun": "1999",
            "Rating": "8,7  "
      },
      {
            "No": "17.",
            "Gambar": "PhotoTop100Film/17.png",
            "Judul": " Goodfellas ",
            "Tahun": "1990",
            "Rating": "8,7  "
      },
      {
            "No": "18.",
            "Gambar": "PhotoTop100Film/18.png",
            "Judul": " One Flew Over the Cuckoo's Nest ",
            "Tahun": "1975",
            "Rating": "8,6  "
      },
      {
            "No": "19.",
            "Gambar": "PhotoTop100Film/19.png",
            "Judul": " Se7en ",
            "Tahun": "1995",
            "Rating": "8,6  "
      },
      {
            "No": "20.",
            "Gambar": "PhotoTop100Film/20.png",
            "Judul": " Seven Samurai ",
            "Tahun": "1954",
            "Rating": "8,6  "
      },
      {
            "No": "21.",
            "Gambar": "PhotoTop100Film/21.png",
            "Judul": " It's a Wonderful Life ",
            "Tahun": "1946",
            "Rating": "8,6  "
      },
      {
            "No": "22.",
            "Gambar": "PhotoTop100Film/22.png",
            "Judul": " The Silence of the Lambs ",
            "Tahun": "1991",
            "Rating": "8,6  "
      },
      {
            "No": "23.",
            "Gambar": "PhotoTop100Film/23.png",
            "Judul": " Saving Private Ryan ",
            "Tahun": "1998",
            "Rating": "8,6  "
      },
      {
            "No": "24.",
            "Gambar": "PhotoTop100Film/24.png",
            "Judul": " City of God ",
            "Tahun": "2002",
            "Rating": "8,6  "
      },
      {
            "No": "25.",
            "Gambar": "PhotoTop100Film/25.png",
            "Judul": " Interstellar ",
            "Tahun": "2014",
            "Rating": "8,6  "
      },
      {
            "No": "26.",
            "Gambar": "PhotoTop100Film/26.png",
            "Judul": " Life Is Beautiful ",
            "Tahun": "1997",
            "Rating": "8,6  "
      },
      {
            "No": "27.",
            "Gambar": "PhotoTop100Film/27.png",
            "Judul": " The Green Mile ",
            "Tahun": "1999",
            "Rating": "8,6  "
      },
      {
            "No": "28.",
            "Gambar": "PhotoTop100Film/28.png",
            "Judul": " Star Wars: Episode IV - A New Hope ",
            "Tahun": "1977",
            "Rating": "8,5  "
      },
      {
            "No": "29.",
            "Gambar": "PhotoTop100Film/29.png",
            "Judul": " Terminator 2: Judgment Day ",
            "Tahun": "1991",
            "Rating": "8,5  "
      },
      {
            "No": "30.",
            "Gambar": "PhotoTop100Film/30.png",
            "Judul": " Back to the Future ",
            "Tahun": "1985",
            "Rating": "8,5  "
      },
      {
            "No": "31.",
            "Gambar": "PhotoTop100Film/31.png",
            "Judul": " Spirited Away ",
            "Tahun": "2001",
            "Rating": "8,5  "
      },
      {
            "No": "32.",
            "Gambar": "PhotoTop100Film/32.png",
            "Judul": " The Pianist ",
            "Tahun": "2002",
            "Rating": "8,5  "
      },
      {
            "No": "33.",
            "Gambar": "PhotoTop100Film/33.png",
            "Judul": " Psycho ",
            "Tahun": "1960",
            "Rating": "8,5  "
      },
      {
            "No": "34.",
            "Gambar": "PhotoTop100Film/34.png",
            "Judul": " Parasite ",
            "Tahun": "2019",
            "Rating": "8,5  "
      },
      {
            "No": "35.",
            "Gambar": "PhotoTop100Film/35.png",
            "Judul": " L\u00e9on: The Professional ",
            "Tahun": "1994",
            "Rating": "8,5  "
      },
      {
            "No": "36.",
            "Gambar": "PhotoTop100Film/36.png",
            "Judul": " The Lion King ",
            "Tahun": "1994",
            "Rating": "8,5  "
      },
      {
            "No": "37.",
            "Gambar": "PhotoTop100Film/37.png",
            "Judul": " Gladiator ",
            "Tahun": "2000",
            "Rating": "8,5  "
      },
      {
            "No": "38.",
            "Gambar": "PhotoTop100Film/38.png",
            "Judul": " American History X ",
            "Tahun": "1998",
            "Rating": "8,5  "
      },
      {
            "No": "39.",
            "Gambar": "PhotoTop100Film/39.png",
            "Judul": " The Departed ",
            "Tahun": "2006",
            "Rating": "8,5  "
      },
      {
            "No": "40.",
            "Gambar": "PhotoTop100Film/40.png",
            "Judul": " The Usual Suspects ",
            "Tahun": "1995",
            "Rating": "8,5  "
      },
      {
            "No": "41.",
            "Gambar": "PhotoTop100Film/41.png",
            "Judul": " The Prestige ",
            "Tahun": "2006",
            "Rating": "8,5  "
      },
      {
            "No": "42.",
            "Gambar": "PhotoTop100Film/42.png",
            "Judul": " Whiplash ",
            "Tahun": "2014",
            "Rating": "8,5  "
      },
      {
            "No": "43.",
            "Gambar": "PhotoTop100Film/43.png",
            "Judul": " Casablanca ",
            "Tahun": "1942",
            "Rating": "8,5  "
      },
      {
            "No": "44.",
            "Gambar": "PhotoTop100Film/44.png",
            "Judul": " Harakiri ",
            "Tahun": "1962",
            "Rating": "8,5  "
      },
      {
            "No": "45.",
            "Gambar": "PhotoTop100Film/45.png",
            "Judul": " Grave of the Fireflies ",
            "Tahun": "1988",
            "Rating": "8,5  "
      },
      {
            "No": "46.",
            "Gambar": "PhotoTop100Film/46.png",
            "Judul": " The Intouchables ",
            "Tahun": "2011",
            "Rating": "8,5  "
      },
      {
            "No": "47.",
            "Gambar": "PhotoTop100Film/47.png",
            "Judul": " Modern Times ",
            "Tahun": "1936",
            "Rating": "8,4  "
      },
      {
            "No": "48.",
            "Gambar": "PhotoTop100Film/48.png",
            "Judul": " Once Upon a Time in the West ",
            "Tahun": "1968",
            "Rating": "8,4  "
      },
      {
            "No": "49.",
            "Gambar": "PhotoTop100Film/49.png",
            "Judul": " Rear Window ",
            "Tahun": "1954",
            "Rating": "8,4  "
      },
      {
            "No": "50.",
            "Gambar": "PhotoTop100Film/50.png",
            "Judul": " Cinema Paradiso ",
            "Tahun": "1988",
            "Rating": "8,4  "
      },
      {
            "No": "51.",
            "Gambar": "PhotoTop100Film/51.png",
            "Judul": " Alien ",
            "Tahun": "1979",
            "Rating": "8,4  "
      },
      {
            "No": "52.",
            "Gambar": "PhotoTop100Film/52.png",
            "Judul": " City Lights ",
            "Tahun": "1931",
            "Rating": "8,4  "
      },
      {
            "No": "53.",
            "Gambar": "PhotoTop100Film/53.png",
            "Judul": " Apocalypse Now ",
            "Tahun": "1979",
            "Rating": "8,4  "
      },
      {
            "No": "54.",
            "Gambar": "PhotoTop100Film/54.png",
            "Judul": " Memento ",
            "Tahun": "2000",
            "Rating": "8,4  "
      },
      {
            "No": "55.",
            "Gambar": "PhotoTop100Film/55.png",
            "Judul": " Django Unchained ",
            "Tahun": "2012",
            "Rating": "8,4  "
      },
      {
            "No": "56.",
            "Gambar": "PhotoTop100Film/56.png",
            "Judul": " Indiana Jones and the Raiders of the Lost Ark ",
            "Tahun": "1981",
            "Rating": "8,4  "
      },
      {
            "No": "57.",
            "Gambar": "PhotoTop100Film/57.png",
            "Judul": " WALL\u00b7E ",
            "Tahun": "2008",
            "Rating": "8,4  "
      },
      {
            "No": "58.",
            "Gambar": "PhotoTop100Film/58.png",
            "Judul": " The Lives of Others ",
            "Tahun": "2006",
            "Rating": "8,4  "
      },
      {
            "No": "59.",
            "Gambar": "PhotoTop100Film/59.png",
            "Judul": " Sunset Blvd",
            "Tahun": " ",
            "Rating": "1950*8,4  "
      },
      {
            "No": "60.",
            "Gambar": "PhotoTop100Film/60.png",
            "Judul": " Paths of Glory ",
            "Tahun": "1957",
            "Rating": "8,4  "
      },
      {
            "No": "61.",
            "Gambar": "PhotoTop100Film/61.png",
            "Judul": " The Shining ",
            "Tahun": "1980",
            "Rating": "8,4  "
      },
      {
            "No": "62.",
            "Gambar": "PhotoTop100Film/62.png",
            "Judul": " The Great Dictator ",
            "Tahun": "1940",
            "Rating": "8,4  "
      },
      {
            "No": "63.",
            "Gambar": "PhotoTop100Film/63.png",
            "Judul": " Avengers: Infinity War ",
            "Tahun": "2018",
            "Rating": "8,4  "
      },
      {
            "No": "64.",
            "Gambar": "PhotoTop100Film/64.png",
            "Judul": " Witness for the Prosecution ",
            "Tahun": "1957",
            "Rating": "8,4  "
      },
      {
            "No": "65.",
            "Gambar": "PhotoTop100Film/65.png",
            "Judul": " Aliens ",
            "Tahun": "1986",
            "Rating": "8,3  "
      },
      {
            "No": "66.",
            "Gambar": "PhotoTop100Film/66.png",
            "Judul": " Spider-Man: Into the Spider-Verse ",
            "Tahun": "2018",
            "Rating": "8,3  "
      },
      {
            "No": "67.",
            "Gambar": "PhotoTop100Film/67.png",
            "Judul": " American Beauty ",
            "Tahun": "1999",
            "Rating": "8,3  "
      },
      {
            "No": "68.",
            "Gambar": "PhotoTop100Film/68.png",
            "Judul": " Dr",
            "Tahun": " Strangelove or: How I Learned to Stop Worrying and Love the Bomb ",
            "Rating": "1964*8,3  "
      },
      {
            "No": "69.",
            "Gambar": "PhotoTop100Film/69.png",
            "Judul": " The Dark Knight Rises ",
            "Tahun": "2012",
            "Rating": "8,3  "
      },
      {
            "No": "70.",
            "Gambar": "PhotoTop100Film/70.png",
            "Judul": " Oldboy ",
            "Tahun": "2003",
            "Rating": "8,3  "
      },
      {
            "No": "71.",
            "Gambar": "PhotoTop100Film/71.png",
            "Judul": " Inglourious Basterds ",
            "Tahun": "2009",
            "Rating": "8,3  "
      },
      {
            "No": "72.",
            "Gambar": "PhotoTop100Film/72.png",
            "Judul": " Amadeus ",
            "Tahun": "1984",
            "Rating": "8,3  "
      },
      {
            "No": "73.",
            "Gambar": "PhotoTop100Film/73.png",
            "Judul": " Coco ",
            "Tahun": "2017",
            "Rating": "8,3  "
      },
      {
            "No": "74.",
            "Gambar": "PhotoTop100Film/74.png",
            "Judul": " Toy Story ",
            "Tahun": "1995",
            "Rating": "8,3  "
      },
      {
            "No": "75.",
            "Gambar": "PhotoTop100Film/75.png",
            "Judul": " Joker ",
            "Tahun": "2019",
            "Rating": "8,3  "
      },
      {
            "No": "76.",
            "Gambar": "PhotoTop100Film/76.png",
            "Judul": " Braveheart ",
            "Tahun": "1995",
            "Rating": "8,3  "
      },
      {
            "No": "77.",
            "Gambar": "PhotoTop100Film/77.png",
            "Judul": " The Boat ",
            "Tahun": "1981",
            "Rating": "8,3  "
      },
      {
            "No": "78.",
            "Gambar": "PhotoTop100Film/78.png",
            "Judul": " Avengers: Endgame ",
            "Tahun": "2019",
            "Rating": "8,3  "
      },
      {
            "No": "79.",
            "Gambar": "PhotoTop100Film/79.png",
            "Judul": " Princess Mononoke ",
            "Tahun": "1997",
            "Rating": "8,3  "
      },
      {
            "No": "80.",
            "Gambar": "PhotoTop100Film/80.png",
            "Judul": " Once Upon a Time in America ",
            "Tahun": "1984",
            "Rating": "8,3  "
      },
      {
            "No": "81.",
            "Gambar": "PhotoTop100Film/81.png",
            "Judul": " Good Will Hunting ",
            "Tahun": "1997",
            "Rating": "8,3  "
      },
      {
            "No": "82.",
            "Gambar": "PhotoTop100Film/82.png",
            "Judul": " Your Name",
            "Tahun": " ",
            "Rating": "2016*8,3  "
      },
      {
            "No": "83.",
            "Gambar": "PhotoTop100Film/83.png",
            "Judul": " Singin' in the Rain ",
            "Tahun": "1952",
            "Rating": "8,3  "
      },
      {
            "No": "84.",
            "Gambar": "PhotoTop100Film/84.png",
            "Judul": " 3 Idiots ",
            "Tahun": "2009",
            "Rating": "8,3  "
      },
      {
            "No": "85.",
            "Gambar": "PhotoTop100Film/85.png",
            "Judul": " Requiem for a Dream ",
            "Tahun": "2000",
            "Rating": "8,3  "
      },
      {
            "No": "86.",
            "Gambar": "PhotoTop100Film/86.png",
            "Judul": " High and Low ",
            "Tahun": "1963",
            "Rating": "8,3  "
      },
      {
            "No": "87.",
            "Gambar": "PhotoTop100Film/87.png",
            "Judul": " Toy Story 3 ",
            "Tahun": "2010",
            "Rating": "8,3  "
      },
      {
            "No": "88.",
            "Gambar": "PhotoTop100Film/88.png",
            "Judul": " Capernaum ",
            "Tahun": "2018",
            "Rating": "8,3  "
      },
      {
            "No": "89.",
            "Gambar": "PhotoTop100Film/89.png",
            "Judul": " Star Wars: Episode VI - Return of the Jedi ",
            "Tahun": "1983",
            "Rating": "8,3  "
      },
      {
            "No": "90.",
            "Gambar": "PhotoTop100Film/90.png",
            "Judul": " Eternal Sunshine of the Spotless Mind ",
            "Tahun": "2004",
            "Rating": "8,3  "
      },
      {
            "No": "91.",
            "Gambar": "PhotoTop100Film/91.png",
            "Judul": " 2001: A Space Odyssey ",
            "Tahun": "1968",
            "Rating": "8,3  "
      },
      {
            "No": "92.",
            "Gambar": "PhotoTop100Film/92.png",
            "Judul": " Reservoir Dogs ",
            "Tahun": "1992",
            "Rating": "8,3  "
      },
      {
            "No": "93.",
            "Gambar": "PhotoTop100Film/93.png",
            "Judul": " Come and See ",
            "Tahun": "1985",
            "Rating": "8,3  "
      },
      {
            "No": "94.",
            "Gambar": "PhotoTop100Film/94.png",
            "Judul": " The Hunt ",
            "Tahun": "2012",
            "Rating": "8,3  "
      },
      {
            "No": "95.",
            "Gambar": "PhotoTop100Film/95.png",
            "Judul": " Citizen Kane ",
            "Tahun": "1941",
            "Rating": "8,3  "
      },
      {
            "No": "96.",
            "Gambar": "PhotoTop100Film/96.png",
            "Judul": " M ",
            "Tahun": "1931",
            "Rating": "8,3  "
      },
      {
            "No": "97.",
            "Gambar": "PhotoTop100Film/97.png",
            "Judul": " Lawrence of Arabia ",
            "Tahun": "1962",
            "Rating": "8,2  "
      },
      {
            "No": "98.",
            "Gambar": "PhotoTop100Film/98.png",
            "Judul": " North by Northwest ",
            "Tahun": "1959",
            "Rating": "8,2  "
      },
      {
            "No": "99.",
            "Gambar": "PhotoTop100Film/99.png",
            "Judul": " Ikiru ",
            "Tahun": "1952",
            "Rating": "8,2  "
      },
      {
            "No": "100.",
            "Gambar": "PhotoTop100Film/100.png",
            "Judul": " Vertigo ",
            "Tahun": "1958",
            "Rating": "8,2  "
      }
]